{"columnCount":12,"allowedComponents":{"components":[],"applicable":false},"columnClassNames":{"text":"aem-GridColumn aem-GridColumn--default--12","title":"aem-GridColumn aem-GridColumn--default--12"},"gridClassNames":"aem-Grid aem-Grid--12 aem-Grid--default--12",":items":{"title":{"linkDisabled":false,"type":"h3","text":"Lorem Ipsum",":type":"core/wcm/components/title/v2/title"},"text":{"text":"\u003Cp\u003ELorem ipsum dolor sit amet, consectetur adipiscing elit, sed do eiusmod tempor incididunt ut labore et dolore magna aliqua. Eu mi bibendum neque egestas congue quisque egestas. Varius morbi enim nunc faucibus a pellentesque. Scelerisque eleifend donec pretium vulputate sapien nec sagittis.\u003C/p\u003E\r\n","richText":true,":type":"core/wcm/components/text/v2/text"}},":itemsOrder":["title","text"],":type":"core/wcm/components/container/v1/container"}